{
  "slug": "1988-ajhsme",
  "title": "1988 AJHSME",
  "description": "Converted from 1988_AJHSME_questions.txt and 1988_AJHSME_solutions.txt.",
  "statementFormat": "HTML",
  "order": 0,
  "status": "DRAFT",
  "topicTags": [
    "ajhsme"
  ],
  "problems": [
    {
      "number": 1,
      "statement": "The diagram shows part of a scale of a measuring device. The arrow indicates an approximate reading of <asy> draw((-3,0)..(0,3)..(3,0)); draw((-3.5,0)--(-2.5,0)); draw((0,2.5)--(0,3.5)); draw((2.5,0)--(3.5,0)); draw((1.8,1.8)--(2.5,2.5)); draw((-1.8,1.8)--(-2.5,2.5)); draw((0,0)--3*dir(120),EndArrow); label(\"$10$\",(-2.6,0),E); label(\"$11$\",(2.6,0),W); </asy> <math>\\text{(A)}\\ 10.05 \\qquad \\text{(B)}\\ 10.15 \\qquad \\text{(C)}\\ 10.25 \\qquad \\text{(D)}\\ 10.3 \\qquad \\text{(E)}\\ 10.6</math>",
      "answerType": "exact",
      "answerKey": "\\ 10.3",
      "points": 1,
      "acceptedAnswers": [
        "D"
      ]
    },
    {
      "number": 2,
      "statement": "The product <imath>8\\times .25\\times 2\\times .125 =</imath> <imath>\\text{(A)}\\ \\frac18 \\qquad \\text{(B)}\\ \\frac14 \\qquad \\text{(C)}\\ \\frac12 \\qquad \\text{(D)}\\ 1 \\qquad \\text{(E)}\\ 2</imath>",
      "answerType": "exact",
      "answerKey": "\\ \\frac 1 2",
      "points": 1,
      "acceptedAnswers": [
        "C"
      ]
    },
    {
      "number": 3,
      "statement": "<imath>\\frac{1}{10}+\\frac{2}{20}+\\frac{3}{30} = </imath> <imath>\\text{(A)}\\ .1 \\qquad \\text{(B)}\\ .123 \\qquad \\text{(C)}\\ .2 \\qquad \\text{(D)}\\ .3 \\qquad \\text{(E)}\\ .6</imath>",
      "answerType": "exact",
      "answerKey": "\\ \\frac 1 3",
      "points": 1,
      "acceptedAnswers": [
        "D"
      ]
    },
    {
      "number": 4,
      "statement": "The figure consists of alternating light and dark squares. The number of dark squares exceeds the number of light squares by <imath>\\text{(A)}\\ 7 \\qquad \\text{(B)}\\ 8 \\qquad \\text{(C)}\\ 9 \\qquad \\text{(D)}\\ 10 \\qquad \\text{(E)}\\ 11</imath> <asy> unitsize(12); //Force a white background in middle even when transparent fill((3,1)--(12,1)--(12,4)--(3,4)--cycle,white); //Black Squares, Gray Border (blends better than white) for(int a=0; a<7; ++a) { filldraw((2a,0)--(2a+1,0)--(2a+1,1)--(2a,1)--cycle,black,gray); } for(int b=7; b<15; ++b) { filldraw((b,14-b)--(b+1,14-b)--(b+1,15-b)--(b,15-b)--cycle,black,gray); } for(int c=1; c<7; ++c) { filldraw((c,c)--(c+1,c)--(c+1,c+1)--(c,c+1)--cycle,black,gray); } filldraw((6,4)--(7,4)--(7,5)--(6,5)--cycle,black,gray); filldraw((7,5)--(8,5)--(8,6)--(7,6)--cycle,black,gray); filldraw((8,4)--(9,4)--(9,5)--(8,5)--cycle,black,gray); //White Squares, Black Border filldraw((7,4)--(8,4)--(8,5)--(7,5)--cycle,white,black); for(int a=0; a<7; ++a) { filldraw((2a+1,0)--(2a+2,0)--(2a+2,1)--(2a+1,1)--cycle,white,black); } for(int b=9; b<15; ++b) { filldraw((b-1,14-b)--(b,14-b)--(b,15-b)--(b-1,15-b)--cycle,white,black); } for(int c=1; c<7; ++c) { filldraw((c+1,c)--(c+2,c)--(c+2,c+1)--(c+1,c+1)--cycle,white,black); } label(\"same\",(6.3,2.45),N); label(\"pattern here\",(7.5,1.4),N); </asy>",
      "answerType": "exact",
      "answerKey": "\\ 8",
      "points": 1,
      "acceptedAnswers": [
        "B"
      ]
    },
    {
      "number": 5,
      "statement": "If <imath>\\angle CBD</imath> is a right angle, then this protractor indicates that the measure of <imath>\\angle ABC</imath> is approximately <asy> unitsize(36); pair A,B,C,D; A=3*dir(160); B=origin; C=3*dir(110); D=3*dir(20); draw((1.5,0)..(0,1.5)..(-1.5,0)); draw((2.5,0)..(0,2.5)..(-2.5,0)--cycle); draw(A--B); draw(C--B); draw(D--B); label(\"O\",(-2.5,0),W); label(\"A\",A,W); label(\"B\",B,S); label(\"C\",C,W); label(\"D\",D,E); label(\"0\",(-1.8,0),W); label(\"20\",(-1.7,.5),NW); label(\"160\",(1.6,.5),NE); label(\"180\",(1.7,0),E); </asy> <imath>\\text{(A)}\\ 20^\\circ \\qquad \\text{(B)}\\ 40^\\circ \\qquad \\text{(C)}\\ 50^\\circ \\qquad \\text{(D)}\\ 70^\\circ \\qquad \\text{(E)}\\ 120^\\circ</imath>",
      "answerType": "exact",
      "answerKey": "\\ 50^ \\circ",
      "points": 1,
      "acceptedAnswers": [
        "C"
      ]
    },
    {
      "number": 6,
      "statement": "<imath>\\frac{(.2)^3}{(.02)^2} =</imath> <imath>\\text{(A)}\\ .2 \\qquad \\text{(B)}\\ 2 \\qquad \\text{(C)}\\ 10 \\qquad \\text{(D)}\\ 15 \\qquad \\text{(E)}\\ 20</imath>",
      "answerType": "exact",
      "answerKey": "\\ 20",
      "points": 1,
      "acceptedAnswers": [
        "E"
      ]
    },
    {
      "number": 7,
      "statement": "<imath>2.46\\times 8.163\\times (5.17+4.829)</imath> is closest to <imath>\\text{(A)}\\ 100 \\qquad \\text{(B)}\\ 200 \\qquad \\text{(C)}\\ 300 \\qquad \\text{(D)}\\ 400 \\qquad \\text{(E)}\\ 500</imath>",
      "answerType": "exact",
      "answerKey": "\\ 200",
      "points": 1,
      "acceptedAnswers": [
        "C"
      ]
    },
    {
      "number": 8,
      "statement": "Betty used a calculator to find the product <imath>0.075 \\times 2.56</imath>. She forgot to enter the decimal points. The calculator showed <imath>19200</imath>. If Betty had entered the decimal points correctly, the answer would have been <imath>\\text{(A)}\\ .0192 \\qquad \\text{(B)}\\ .192 \\qquad \\text{(C)}\\ 1.92 \\qquad \\text{(D)}\\ 19.2 \\qquad \\text{(E)}\\ 192</imath> ==Solution 1== Betty calculated <imath>75 \\times 256 = 19200</imath>, when she should have calculated <imath>\\frac{75}{1000}\\times\\frac{256}{100} = \\frac{19200}{100000} = \\frac{192}{1000} = \\boxed{\\textbf{(B)}\\ .192}</imath>.",
      "answerType": "exact",
      "answerKey": "\\ .192",
      "points": 1,
      "acceptedAnswers": [
        "B"
      ]
    },
    {
      "number": 9,
      "statement": "An isosceles triangle is a triangle with two sides of equal length. How many of the five triangles on the square grid below are isosceles? <asy> for(int a=0; a<12; ++a) { draw((a,0)--(a,6)); } for(int b=0; b<7; ++b) { draw((0,b)--(11,b)); } draw((0,6)--(2,6)--(1,4)--cycle,linewidth(3)); draw((3,4)--(3,6)--(5,4)--cycle,linewidth(3)); draw((0,1)--(3,2)--(6,1)--cycle,linewidth(3)); draw((7,4)--(6,6)--(9,4)--cycle,linewidth(3)); draw((8,1)--(9,3)--(10,0)--cycle,linewidth(3)); </asy> <imath>\\text{(A)}\\ 1 \\qquad \\text{(B)}\\ 2 \\qquad \\text{(C)}\\ 3 \\qquad \\text{(D)}\\ 4 \\qquad \\text{(E)}\\ 5</imath>",
      "answerType": "exact",
      "answerKey": "\\ 4",
      "points": 1,
      "acceptedAnswers": [
        "D"
      ]
    },
    {
      "number": 10,
      "statement": "Chris' birthday is on a Thursday this year. What day of the week will it be <imath>60</imath> days after her birthday? <imath>\\text{(A)}\\ \\text{Monday} \\qquad \\text{(B)}\\ \\text{Wednesday} \\qquad \\text{(C)}\\ \\text{Thursday} \\qquad \\text{(D)}\\ \\text{Friday} \\qquad \\text{(E)}\\ \\text{Saturday}</imath>",
      "answerType": "exact",
      "answerKey": "\\ Monday",
      "points": 1,
      "acceptedAnswers": [
        "A"
      ]
    },
    {
      "number": 11,
      "statement": "<imath>\\sqrt{164}</imath> is <imath>\\text{(A)}\\ 42 \\qquad \\text{(B)}\\ \\text{less than }10 \\qquad \\text{(C)}\\ \\text{between }10\\text{ and }11 \\qquad \\text{(D)}\\ \\text{between }11\\text{ and }12 \\qquad \\text{(E)}\\ \\text{between }12\\text{ and }13</imath>",
      "answerType": "exact",
      "answerKey": "\\ between 12 and 13",
      "points": 1,
      "acceptedAnswers": [
        "E"
      ]
    },
    {
      "number": 12,
      "statement": "Suppose the estimated <imath>20</imath> billion dollar cost to send a person to the planet Mars is shared equally by the <imath>250</imath> million people in the U.S. Then each person's share is <imath>\\text{(A)}\\ 40\\text{ dollars} \\qquad \\text{(B)}\\ 50\\text{ dollars} \\qquad \\text{(C)}\\ 80\\text{ dollars} \\qquad \\text{(D)}\\ 100\\text{ dollars} \\qquad \\text{(E)}\\ 125\\text{ dollars}</imath>",
      "answerType": "exact",
      "answerKey": "\\ \\$80",
      "points": 1,
      "acceptedAnswers": [
        "C"
      ]
    },
    {
      "number": 13,
      "statement": "If rose bushes are spaced about <imath>1</imath> foot apart, approximately how many bushes are needed to surround a circular patio whose radius is <imath>12</imath> feet? <imath>\\text{(A)}\\ 12 \\qquad \\text{(B)}\\ 38 \\qquad \\text{(C)}\\ 48 \\qquad \\text{(D)}\\ 75 \\qquad \\text{(E)}\\ 450</imath>",
      "answerType": "exact",
      "answerKey": "\\ 75",
      "points": 1,
      "acceptedAnswers": [
        "D"
      ]
    },
    {
      "number": 14,
      "statement": "<imath>\\diamondsuit </imath> and <imath>\\Delta </imath> are whole numbers and <imath>\\diamondsuit \\times \\Delta =36</imath>. The largest possible value of <imath>\\diamondsuit + \\Delta </imath> is <imath>\\text{(A)}\\ 12 \\qquad \\text{(B)}\\ 13 \\qquad \\text{(C)}\\ 15 \\qquad \\text{(D)}\\ 20\\ \\qquad \\text{(E)}\\ 37</imath>",
      "answerType": "exact",
      "answerKey": "\\ 37",
      "points": 1,
      "acceptedAnswers": [
        "E"
      ]
    },
    {
      "number": 15,
      "statement": "The reciprocal of <math>\\left( \\frac{1}{2}+\\frac{1}{3}\\right)</math> is <math>\\text{(A)}\\ \\frac{1}{6} \\qquad \\text{(B)}\\ \\frac{2}{5} \\qquad \\text{(C)}\\ \\frac{6}{5} \\qquad \\text{(D)}\\ \\frac{5}{2} \\qquad \\text{(E)}\\ 5</math>",
      "answerType": "exact",
      "answerKey": "\\ \\frac 6 5",
      "points": 1,
      "acceptedAnswers": [
        "C"
      ]
    },
    {
      "number": 16,
      "statement": "Placing no more than one <imath>\\text{X}</imath> in each small square, what is the greatest number of <imath>\\text{X}</imath>'s that can be put on the grid shown without getting three <imath>\\text{X}</imath>'s in a row vertically, horizontally, or diagonally? <imath>\\text{(A)}\\ 2 \\qquad \\text{(B)}\\ 3 \\qquad \\text{(C)}\\ 4 \\qquad \\text{(D)}\\ 5 \\qquad \\text{(E)}\\ 6</imath> <asy> for(int a=0; a<4; ++a) { draw((a,0)--(a,3)); } for(int b=0; b<4; ++b) { draw((0,b)--(3,b)); } </asy>",
      "answerType": "exact",
      "answerKey": "\\ 6",
      "points": 1,
      "acceptedAnswers": [
        "E"
      ]
    },
    {
      "number": 17,
      "statement": "The shaded region formed by the two intersecting perpendicular rectangles, in square units, is <asy> fill((0,0)--(6,0)--(6,-3.5)--(9,-3.5)--(9,0)--(10,0)--(10,2)--(9,2)--(9,4.5)--(6,4.5)--(6,2)--(0,2)--cycle,black); label(\"2\",(0,.9),W); label(\"3\",(7.3,4.5),N); draw((0,-3.3)--(0,-5.3),linewidth(1)); draw((0,-4.3)--(3.7,-4.3),linewidth(1)); label(\"10\",(4.7,-3.7),S); draw((5.7,-4.3)--(10,-4.3),linewidth(1)); draw((10,-3.3)--(10,-5.3),linewidth(1)); draw((11,4.5)--(13,4.5),linewidth(1)); draw((12,4.5)--(12,2),linewidth(1)); label(\"8\",(11.3,1),E); draw((12,0)--(12,-3.5),linewidth(1)); draw((11,-3.5)--(13,-3.5),linewidth(1)); </asy> <imath>\\text{(A)}\\ 23 \\qquad \\text{(B)}\\ 38 \\qquad \\text{(C)}\\ 44 \\qquad \\text{(D)}\\ 46 \\qquad \\text{(E)}\\ \\text{unable to be determined from the information given}</imath>",
      "answerType": "exact",
      "answerKey": "\\ 38",
      "points": 1,
      "acceptedAnswers": [
        "B"
      ]
    },
    {
      "number": 18,
      "statement": "The average weight of <imath>6</imath> boys is <imath>150</imath> pounds and the average weight of <imath>4</imath> girls is <imath>120</imath> pounds. The average weight of the <imath>10</imath> children is <imath>\\text{(A)}\\ 135\\text{ pounds} \\qquad \\text{(B)}\\ 137\\text{ pounds} \\qquad \\text{(C)}\\ 138\\text{ pounds} \\qquad \\text{(D)}\\ 140\\text{ pounds} \\qquad \\text{(E)}\\ 141\\text{ pounds}</imath>",
      "answerType": "exact",
      "answerKey": "\\ 138",
      "points": 1,
      "acceptedAnswers": [
        "C"
      ]
    },
    {
      "number": 19,
      "statement": "What is the <imath>100\\text{th}</imath> number in the arithmetic sequence: <imath>1,5,9,13,17,21,25,...</imath>? <imath>\\text{(A)}\\ 397 \\qquad \\text{(B)}\\ 399 \\qquad \\text{(C)}\\ 401 \\qquad \\text{(D)}\\ 403 \\qquad \\text{(E)}\\ 405</imath>",
      "answerType": "exact",
      "answerKey": "\\ 397",
      "points": 1,
      "acceptedAnswers": [
        "A"
      ]
    },
    {
      "number": 20,
      "statement": "The glass gauge on a cylindrical coffee maker shows that there are <imath>45</imath> cups left when the coffee maker is <imath>36\\% </imath> full. How many cups of coffee does it hold when it is full? <imath>\\text{(A)}\\ 80 \\qquad \\text{(B)}\\ 100 \\qquad \\text{(C)}\\ 125 \\qquad \\text{(D)}\\ 130 \\qquad \\text{(E)}\\ 262</imath> <asy> draw((5,0)..(0,-1.3)..(-5,0)); draw((5,0)--(5,10)); draw((-5,0)--(-5,10)); draw(ellipse((0,10),5,1.3)); draw(circle((.3,1.3),.4)); draw((-.1,1.7)--(-.1,7.9)--(.7,7.9)--(.7,1.7)--cycle); fill((-.1,1.7)--(-.1,4)--(.7,4)--(.7,1.7)--cycle,black); draw((-2,11.3)--(2,11.3)..(2.6,11.9)..(2,12.2)--(-2,12.2)..(-2.6,11.9)..cycle); </asy>",
      "answerType": "exact",
      "answerKey": "\\ 125",
      "points": 1,
      "acceptedAnswers": [
        "C"
      ]
    },
    {
      "number": 21,
      "statement": "A fifth number, <imath>n</imath>, is added to the set <imath>\\{ 3,6,9,10 \\}</imath> to make the mean of the set of five numbers equal to its median. The number of possible values of <imath>n</imath> is <imath>\\text{(A)}\\ 1 \\qquad \\text{(B)}\\ 2 \\qquad \\text{(C)}\\ 3 \\qquad \\text{(D)}\\ 4 \\qquad \\text{(E)}\\ \\text{more than }4</imath>",
      "answerType": "exact",
      "answerKey": "\\ 3",
      "points": 1,
      "acceptedAnswers": [
        "C"
      ]
    },
    {
      "number": 22,
      "statement": "Tom's Hat Shoppe increased all original prices by <imath>25\\% </imath>. Now the shoppe is having a sale where all prices are <imath>20\\% </imath> off these increased prices. Which statement best describes the sale price of an item? <imath>\\text{(A)}\\ \\text{The sale price is }5\\% \\text{ higher than the original price.}</imath> <imath>\\text{(B)}\\ \\text{The sale price is higher than the original price, but by less than }5\\% .</imath> <imath>\\text{(C)}\\ \\text{The sale price is higher than the original price, but by more than }5\\% .</imath> <imath>\\text{(D)}\\ \\text{The sale price is lower than the original price.}</imath> <imath>\\text{(E)}\\ \\text{The sale price is the same as the original price.}</imath>",
      "answerType": "exact",
      "answerKey": "\\ The sale price the same as the original price",
      "points": 1,
      "acceptedAnswers": [
        "E"
      ]
    },
    {
      "number": 23,
      "statement": "Maria buys computer disks at a price of <imath>4</imath> for <imath>\\$5</imath> and sells them at a price of <imath>3</imath> for <imath>\\$5</imath>. How many computer disks must she sell in order to make a profit of <imath>\\$100</imath>? <imath>\\text{(A)}\\ 100 \\qquad \\text{(B)}\\ 120 \\qquad \\text{(C)}\\ 200 \\qquad \\text{(D)}\\ 240 \\qquad \\text{(E)}\\ 1200</imath>",
      "answerType": "exact",
      "answerKey": "\\ 240",
      "points": 1,
      "acceptedAnswers": [
        "C"
      ]
    },
    {
      "number": 24,
      "statement": "<asy> unitsize(15); for (int a=0; a<6; ++a) { draw(2*dir(60a)--2*dir(60a+60),linewidth(1)); } draw((1,1.7320508075688772935274463415059)--(1,3.7320508075688772935274463415059)--(-1,3.7320508075688772935274463415059)--(-1,1.7320508075688772935274463415059)--cycle,linewidth(1)); fill((.4,1.7320508075688772935274463415059)--(0,3.35)--(-.4,1.7320508075688772935274463415059)--cycle,black); label(\"1.\",(0,-2),S); draw(arc((1,1.7320508075688772935274463415059),1,90,300,CW)); draw((1.5,0.86602540378443864676372317075294)--(1.75,1.7)); draw((1.5,0.86602540378443864676372317075294)--(2.2,1)); draw((7,0)--(6,1.7320508075688772935274463415059)--(4,1.7320508075688772935274463415059)--(3,0)--(4,-1.7320508075688772935274463415059)--(6,-1.7320508075688772935274463415059)--cycle,linewidth(1)); draw((7,0)--(6,1.7320508075688772935274463415059)--(7.7320508075688772935274463415059,2.7320508075688772935274463415059)--(8.7320508075688772935274463415059,1)--cycle,linewidth(1)); label(\"2.\",(5,-2),S); draw(arc((7,0),1,30,240,CW)); draw((6.5,-0.86602540378443864676372317075294)--(7.1,-.7)); draw((6.5,-0.86602540378443864676372317075294)--(6.8,-1.5)); draw((14,0)--(13,1.7320508075688772935274463415059)--(11,1.7320508075688772935274463415059)--(10,0)--(11,-1.7320508075688772935274463415059)--(13,-1.7320508075688772935274463415059)--cycle,linewidth(1)); draw((14,0)--(13,-1.7320508075688772935274463415059)--(14.7320508075688772935274463415059,-2.7320508075688772935274463415059)--(15.7320508075688772935274463415059,-1)--cycle,linewidth(1)); label(\"3.\",(12,-2.5),S); draw((21,0)--(20,1.7320508075688772935274463415059)--(18,1.7320508075688772935274463415059)--(17,0)--(18,-1.7320508075688772935274463415059)--(20,-1.7320508075688772935274463415059)--cycle,linewidth(1)); draw((18,-1.7320508075688772935274463415059)--(20,-1.7320508075688772935274463415059)--(20,-3.7320508075688772935274463415059)--(18,-3.7320508075688772935274463415059)--cycle,linewidth(1)); label(\"4.\",(19,-4),S); </asy> The square in the first diagram \"rolls\" clockwise around the fixed regular hexagon until it reaches the bottom. In which position will the solid triangle be in diagram <imath>4</imath>? <asy> unitsize(12); label(\"(A)\",(0,0),W); fill((1,-1)--(1,1)--(5,0)--cycle,black); label(\"(B)\",(6,0),E); fill((9,-2)--(11,-2)--(10,1)--cycle,black); label(\"(C)\",(14,0),E); fill((17,1)--(19,1)--(18,-1.8)--cycle,black); label(\"(D)\",(22,0),E); fill((25,-1)--(27,-2)--(28,1)--cycle,black); label(\"(E)\",(31,0),E); fill((33,0)--(37,1)--(37,-1)--cycle,black); </asy>",
      "answerType": "multiple",
      "answerKey": "A",
      "points": 1
    },
    {
      "number": 25,
      "statement": "A '''[[palindrome]]''' is a [[whole number]] that reads the same forwards and backwards. If one neglects the colon, certain times displayed on a digital watch are palindromes. Three examples are: <imath>\\boxed{1:01}</imath>, <imath>\\boxed{4:44}</imath>, and <imath>\\boxed{12:21}</imath>. How many times during a <imath>12</imath>-hour period will be palindromes? <imath>\\text{(A)}\\ 57 \\qquad \\text{(B)}\\ 60 \\qquad \\text{(C)}\\ 63 \\qquad \\text{(D)}\\ 90 \\qquad \\text{(E)}\\ 93</imath>",
      "answerType": "exact",
      "answerKey": "\\ 57",
      "points": 1,
      "acceptedAnswers": [
        "C"
      ]
    }
  ]
}
